b2bsaas2saas/__init__.py
b2bsaas2saas/main.py
b2bsaas2saas-0.1.2.dist-info/licenses/LICENSE
b2bsaas2saas-0.1.2.dist-info/METADATA
b2bsaas2saas-0.1.2.dist-info/WHEEL
b2bsaas2saas-0.1.2.dist-info/entry_points.txt
b2bsaas2saas-0.1.2.dist-info/top_level.txt
b2bsaas2saas-0.1.2.dist-info/RECORD
